var PIP = {
"type": "FeatureCollection",
"name": "PIP_ET_TdP",
"crs": { "type": "name", "properties": { "name": "urn:ogc:def:crs:OGC:1.3:CRS84" } },
"features": [
{ "type": "Feature", "properties": { "OBJECTID": 1984905, "SHAPESTAre": 469.1923828125, "SHAPESTLen": 88.626407306363561, "NrRNET": "-", "Denominaca": "Av. Hotel", "TipologiaE": "Hotel", "Categoria": "4", "NrUnidAloj": 70, "NrCamasFix": 124, "NrQuartos": 70, "NrSuites": 0, "NrApart": 0, "NrMoradias": 0, "Alteracoes": "Não", "NovasUnidA": 70, "NovasCamas": 124, "DataDespac": "2018\/08\/03", "IntegraCT": "NaoIntegra", "Designacao": "n.a.", "CampoGolfe": "Não", "SalasReuni": "Não", "SPA": null, "OutrosEqui": null, "Endereco": "Av da Republica, 594", "Localidade": "Matosinhos", "LatLong": "41,1800652086103 ; -8,6860545644298", "Fiabilidad": "Fiavel", "Freguesia": "União das freguesias de Matosinhos e Leça da Palmeira", "Concelho": "Matosinhos", "Distrito": "Porto", "NUTSIII": "Área Metropolitana do Porto", "NUTSII": "Norte", "NUTSI": "Continente", "ERT": "Turismo do Porto e Norte de Portugal", "PNCT": "Não Abrangido", "RNAP": "Não Abrangido", "RedeNatura": "Não Abrangido", "RedeNatu_1": "Não Abrangido", "RedeNatu_2": "Não Abrangido", "FaixaCoste": "Faixa Costeira (5km)", "ZonaCostei": "Zona Costeira (2km)", "ZonaTerres": "Não Abrangido", "LimitePROT": "Norte", "LimitePOC": "Não Abrangido", "LimiteAlbu": "Não Abrangido", "UNESCO": "Não Abrangido", "Geoparques": "Não Abrangido", "Biosfera": "Não Abrangido", "RedeAldeia": "Não Abrangido", "Freguesias": "Sim", "NUTSIIICos": "Sim", "EstacaoNau": "Não Abrangido", "DataAtuali": "2018\/10\/10", "RNET": null, "Type_shp": "PIP de ET com Parecer Favoravel do TdP" }, "geometry": { "type": "Point", "coordinates": [ -8.686059216232898, 41.180065462505219 ] } }
]
}
